src/__init__.py
src/config.py
src/server.py
src/api/__init__.py
src/api/health_endpoints.py
src/auth/__init__.py
src/auth/api_keys.py
src/auth/permissions.py
src/dao/__init__.py
src/dao/agent_dao.py
src/dao/artifact_dao.py
src/dao/base.py
src/dao/plan_dao.py
src/dao/task_dao.py
src/database/__init__.py
src/database/connection_pool.py
src/database/init_validation.py
src/database/models.py
src/database/schema.sql
src/database/session.py
src/database/engines/__init__.py
src/database/engines/postgresql.py
src/database/engines/sqlite.py
src/middleware/__init__.py
src/middleware/audit.py
src/middleware/auth.py
src/middleware/error_handler.py
src/middleware/logging.py
src/middleware/mcp_auth.py
src/models/__init__.py
src/models/agent.py
src/models/artifact.py
src/models/metadata_schemas.py
src/models/plan.py
src/models/task.py
src/monitoring/__init__.py
src/monitoring/health.py
src/monitoring/metrics.py
src/services/__init__.py
src/services/agent_service.py
src/services/artifact_service.py
src/services/assignment_service.py
src/services/audit_service.py
src/services/plan_service.py
src/services/session_service.py
src/services/task_service.py
src/tools/__init__.py
src/tools/agent_tools.py
src/tools/artifact_tools.py
src/tools/assignment_tools.py
src/tools/batch_tools.py
src/tools/completion_handler_tools.py
src/tools/database_init_tool.py
src/tools/database_migration_tool.py
src/tools/database_setup_tools.py
src/tools/dependency_tools.py
src/tools/file_ownership_tools.py
src/tools/parallel_execution_tools.py
src/tools/plan_tools.py
src/tools/review_workflow_tools.py
src/tools/security_wrapper.py
src/tools/task_tools.py
src/tools/tool_validator.py
src/tools/tool_wrapper.py
src/tools/workflow_automation_tools.py
src/utils/__init__.py
src/utils/audit_logger.py
src/utils/capability_matcher.py
src/utils/metadata_utils.py
src/utils/plan_validator.py
src/utils/transaction_manager.py
src/utils/tree_builder.py
coord_hub_lite_mcp-0.1.3.dist-info/METADATA
coord_hub_lite_mcp-0.1.3.dist-info/WHEEL
coord_hub_lite_mcp-0.1.3.dist-info/entry_points.txt
coord_hub_lite_mcp-0.1.3.dist-info/top_level.txt
coord_hub_lite_mcp-0.1.3.dist-info/RECORD
