Metadata-Version: 2.4
Name: coord-hub-lite-mcp
Version: 0.1.3
Summary: Coord-Hub-Lite: stdio MCP server for agentic SWE orchestration
Author: Coord-Hub Team
License: Apache-2.0
Keywords: mcp,claude,fastmcp,agents,orchestration
Requires-Python: >=3.10
Requires-Dist: fastmcp>=0.1.0
Requires-Dist: SQLAlchemy>=2.0.0
Requires-Dist: aiosqlite>=0.19.0
Requires-Dist: pydantic>=2.6.0
Requires-Dist: pydantic-settings>=2.2.0
Requires-Dist: httpx>=0.24.0
Requires-Dist: prometheus-client>=0.20.0
Requires-Dist: PyJWT>=2.8.0
Requires-Dist: structlog>=24.1.0
Requires-Dist: greenlet>=3.0.3
